[
  {
    "ContainingType": "AcountService.Controllers.AuthenticateController",
    "Method": "LoginUserAsync",
    "RelativePath": "api/Authenticate/login",
    "HttpMethod": "POST",
    "IsController": true,
    "Order": 0,
    "Parameters": [
      {
        "Name": "userLoginRequest",
        "Type": "AcountService.dto.request.accountservice.UserLoginRequest",
        "IsRequired": true
      }
    ],
    "ReturnTypes": []
  },
  {
    "ContainingType": "AcountService.Controllers.AuthenticateController",
    "Method": "LogoutUser",
    "RelativePath": "api/Authenticate/logout-user",
    "HttpMethod": "DELETE",
    "IsController": true,
    "Order": 0,
    "Parameters": [
      {
        "Name": "request",
        "Type": "AcountService.dto.request.accountservice.LogoutRequest",
        "IsRequired": true
      }
    ],
    "ReturnTypes": []
  },
  {
    "ContainingType": "AcountService.Controllers.AuthenticateController",
    "Method": "RefreshTokenAsync",
    "RelativePath": "api/Authenticate/refresh-token",
    "HttpMethod": "POST",
    "IsController": true,
    "Order": 0,
    "Parameters": [
      {
        "Name": "request",
        "Type": "AcountService.dto.request.accountservice.TokenRefreshRequest",
        "IsRequired": true
      }
    ],
    "ReturnTypes": []
  },
  {
    "ContainingType": "AcountService.Controllers.CartController",
    "Method": "AddProductAsync",
    "RelativePath": "api/Cart",
    "HttpMethod": "POST",
    "IsController": true,
    "Order": 0,
    "Parameters": [
      {
        "Name": "request",
        "Type": "AcountService.dto.request.cart.AddProductToCartRequest",
        "IsRequired": true
      }
    ],
    "ReturnTypes": []
  },
  {
    "ContainingType": "AcountService.Controllers.CartController",
    "Method": "UpdateQuantityInCart",
    "RelativePath": "api/Cart",
    "HttpMethod": "PUT",
    "IsController": true,
    "Order": 0,
    "Parameters": [
      {
        "Name": "request",
        "Type": "AcountService.dto.request.cart.UpdateQuantityInCartRequest",
        "IsRequired": true
      }
    ],
    "ReturnTypes": []
  },
  {
    "ContainingType": "AcountService.Controllers.CartController",
    "Method": "GetListProductAsync",
    "RelativePath": "api/Cart",
    "HttpMethod": "GET",
    "IsController": true,
    "Order": 0,
    "Parameters": [],
    "ReturnTypes": []
  },
  {
    "ContainingType": "AcountService.Controllers.CartController",
    "Method": "DeleteProductInCart",
    "RelativePath": "api/Cart/{CartProductId}",
    "HttpMethod": "DELETE",
    "IsController": true,
    "Order": 0,
    "Parameters": [
      {
        "Name": "CartProductId",
        "Type": "System.Int32",
        "IsRequired": true
      }
    ],
    "ReturnTypes": []
  },
  {
    "ContainingType": "AcountService.Controllers.CategoryController",
    "Method": "AddCategoryAsync",
    "RelativePath": "api/Category",
    "HttpMethod": "POST",
    "IsController": true,
    "Order": 0,
    "Parameters": [
      {
        "Name": "request",
        "Type": "AcountService.dto.request.Category.CreateCategoryRequest",
        "IsRequired": true
      }
    ],
    "ReturnTypes": []
  },
  {
    "ContainingType": "AcountService.Controllers.CategoryController",
    "Method": "UpdateCategoryAsync",
    "RelativePath": "api/Category/{categoryId}",
    "HttpMethod": "PUT",
    "IsController": true,
    "Order": 0,
    "Parameters": [
      {
        "Name": "categoryId",
        "Type": "System.Int32",
        "IsRequired": true
      },
      {
        "Name": "request",
        "Type": "AcountService.dto.request.Category.UpdateCategoryRequest",
        "IsRequired": true
      }
    ],
    "ReturnTypes": []
  },
  {
    "ContainingType": "AcountService.Controllers.CategoryController",
    "Method": "DeleteCategoryAsync",
    "RelativePath": "api/Category/{id}",
    "HttpMethod": "DELETE",
    "IsController": true,
    "Order": 0,
    "Parameters": [
      {
        "Name": "id",
        "Type": "System.Int32",
        "IsRequired": true
      }
    ],
    "ReturnTypes": []
  },
  {
    "ContainingType": "AcountService.Controllers.DiscountController",
    "Method": "CreateDiscount",
    "RelativePath": "api/Discount",
    "HttpMethod": "POST",
    "IsController": true,
    "Order": 0,
    "Parameters": [
      {
        "Name": "resquest",
        "Type": "AcountService.dto.request.discount.DiscountResquest",
        "IsRequired": true
      }
    ],
    "ReturnTypes": []
  },
  {
    "ContainingType": "AcountService.Controllers.DiscountController",
    "Method": "ConfrimCode",
    "RelativePath": "api/Discount/{code}",
    "HttpMethod": "GET",
    "IsController": true,
    "Order": 0,
    "Parameters": [
      {
        "Name": "code",
        "Type": "System.String",
        "IsRequired": true
      }
    ],
    "ReturnTypes": []
  },
  {
    "ContainingType": "AcountService.Controllers.OrderControler",
    "Method": "GetOrderInfo",
    "RelativePath": "api/OrderControler",
    "HttpMethod": "POST",
    "IsController": true,
    "Order": 0,
    "Parameters": [
      {
        "Name": "request",
        "Type": "AcountService.dto.request.Order.OrderRequest",
        "IsRequired": true
      }
    ],
    "ReturnTypes": []
  },
  {
    "ContainingType": "AcountService.Controllers.ProductController",
    "Method": "GetListProductAsync",
    "RelativePath": "api/Product",
    "HttpMethod": "GET",
    "IsController": true,
    "Order": 0,
    "Parameters": [
      {
        "Name": "page",
        "Type": "System.Int32",
        "IsRequired": false
      },
      {
        "Name": "size",
        "Type": "System.Int32",
        "IsRequired": false
      }
    ],
    "ReturnTypes": []
  },
  {
    "ContainingType": "AcountService.Controllers.ProductController",
    "Method": "UpdateProductAsync",
    "RelativePath": "api/Product/{id}",
    "HttpMethod": "PUT",
    "IsController": true,
    "Order": 0,
    "Parameters": [
      {
        "Name": "id",
        "Type": "System.Int32",
        "IsRequired": true
      },
      {
        "Name": "Name",
        "Type": "System.String",
        "IsRequired": false
      },
      {
        "Name": "Description",
        "Type": "System.String",
        "IsRequired": false
      },
      {
        "Name": "Price",
        "Type": "System.Decimal",
        "IsRequired": false
      },
      {
        "Name": "UrlImage",
        "Type": "Microsoft.AspNetCore.Http.IFormFile",
        "IsRequired": false
      },
      {
        "Name": "CategoryId",
        "Type": "System.Int32",
        "IsRequired": false
      },
      {
        "Name": "StockQuantity",
        "Type": "System.Int32",
        "IsRequired": false
      }
    ],
    "ReturnTypes": []
  },
  {
    "ContainingType": "AcountService.Controllers.ProductController",
    "Method": "DeleteProduct",
    "RelativePath": "api/Product/{id}",
    "HttpMethod": "DELETE",
    "IsController": true,
    "Order": 0,
    "Parameters": [
      {
        "Name": "id",
        "Type": "System.Int32",
        "IsRequired": true
      }
    ],
    "ReturnTypes": []
  },
  {
    "ContainingType": "AcountService.Controllers.ProductController",
    "Method": "GetProductAsync",
    "RelativePath": "api/Product/{id}",
    "HttpMethod": "GET",
    "IsController": true,
    "Order": 0,
    "Parameters": [
      {
        "Name": "id",
        "Type": "System.Int32",
        "IsRequired": true
      }
    ],
    "ReturnTypes": []
  },
  {
    "ContainingType": "AcountService.Controllers.ProductController",
    "Method": "GetListProductInCategoryId",
    "RelativePath": "api/Product/category/{categoryId}",
    "HttpMethod": "GET",
    "IsController": true,
    "Order": 0,
    "Parameters": [
      {
        "Name": "categoryId",
        "Type": "System.Int32",
        "IsRequired": true
      },
      {
        "Name": "page",
        "Type": "System.Int32",
        "IsRequired": false
      },
      {
        "Name": "size",
        "Type": "System.Int32",
        "IsRequired": false
      }
    ],
    "ReturnTypes": []
  },
  {
    "ContainingType": "AcountService.Controllers.ProductController",
    "Method": "AddProductAsync",
    "RelativePath": "api/Product/product",
    "HttpMethod": "POST",
    "IsController": true,
    "Order": 0,
    "Parameters": [
      {
        "Name": "Name",
        "Type": "System.String",
        "IsRequired": false
      },
      {
        "Name": "Description",
        "Type": "System.String",
        "IsRequired": false
      },
      {
        "Name": "Price",
        "Type": "System.Decimal",
        "IsRequired": false
      },
      {
        "Name": "UrlImage",
        "Type": "Microsoft.AspNetCore.Http.IFormFile",
        "IsRequired": false
      },
      {
        "Name": "CategoryId",
        "Type": "System.Int32",
        "IsRequired": false
      },
      {
        "Name": "StockQuantity",
        "Type": "System.Int32",
        "IsRequired": false
      }
    ],
    "ReturnTypes": []
  },
  {
    "ContainingType": "AcountService.Controllers.ProductController",
    "Method": "UpdateStockAsync",
    "RelativePath": "api/Product/Stock/{id}",
    "HttpMethod": "PUT",
    "IsController": true,
    "Order": 0,
    "Parameters": [
      {
        "Name": "request",
        "Type": "AcountService.dto.request.product.UpdateStockProductRequest",
        "IsRequired": true
      },
      {
        "Name": "id",
        "Type": "",
        "IsRequired": true
      }
    ],
    "ReturnTypes": []
  },
  {
    "ContainingType": "BanVatLieuXayDung.Controllers.PromotionalController",
    "Method": "GetAllPromotional",
    "RelativePath": "api/Promotional",
    "HttpMethod": "GET",
    "IsController": true,
    "Order": 0,
    "Parameters": [],
    "ReturnTypes": []
  },
  {
    "ContainingType": "BanVatLieuXayDung.Controllers.PromotionalController",
    "Method": "CreatePromotional",
    "RelativePath": "api/Promotional",
    "HttpMethod": "POST",
    "IsController": true,
    "Order": 0,
    "Parameters": [
      {
        "Name": "request",
        "Type": "BanVatLieuXayDung.dto.request.Promotional.CreatePromotionalRequest",
        "IsRequired": true
      }
    ],
    "ReturnTypes": []
  },
  {
    "ContainingType": "BanVatLieuXayDung.Controllers.PromotionalController",
    "Method": "GetPromotional",
    "RelativePath": "api/Promotional/{productId}",
    "HttpMethod": "GET",
    "IsController": true,
    "Order": 0,
    "Parameters": [
      {
        "Name": "productId",
        "Type": "System.Int32",
        "IsRequired": true
      }
    ],
    "ReturnTypes": []
  },
  {
    "ContainingType": "BanVatLieuXayDung.Controllers.PromotionalController",
    "Method": "UpdatePromotional",
    "RelativePath": "api/Promotional/{saleId}",
    "HttpMethod": "PUT",
    "IsController": true,
    "Order": 0,
    "Parameters": [
      {
        "Name": "saleId",
        "Type": "System.Int32",
        "IsRequired": true
      },
      {
        "Name": "request",
        "Type": "BanVatLieuXayDung.dto.request.Promotional.UpdatePromotionalRequest",
        "IsRequired": true
      }
    ],
    "ReturnTypes": []
  },
  {
    "ContainingType": "BanVatLieuXayDung.Controllers.PromotionalController",
    "Method": "DeletePromotional",
    "RelativePath": "api/Promotional/{saleId}",
    "HttpMethod": "DELETE",
    "IsController": true,
    "Order": 0,
    "Parameters": [
      {
        "Name": "saleId",
        "Type": "System.Int32",
        "IsRequired": true
      }
    ],
    "ReturnTypes": []
  },
  {
    "ContainingType": "AcountService.Controllers.SendEmailController",
    "Method": "ConfirmEmail",
    "RelativePath": "api/SendEmail/confirm-email",
    "HttpMethod": "POST",
    "IsController": true,
    "Order": 0,
    "Parameters": [
      {
        "Name": "request",
        "Type": "AcountService.dto.request.email.EmailConfrimRequest",
        "IsRequired": true
      }
    ],
    "ReturnTypes": []
  },
  {
    "ContainingType": "AcountService.Controllers.UserController",
    "Method": "GetUser",
    "RelativePath": "api/User/{id}",
    "HttpMethod": "GET",
    "IsController": true,
    "Order": 0,
    "Parameters": [
      {
        "Name": "id",
        "Type": "System.String",
        "IsRequired": true
      }
    ],
    "ReturnTypes": []
  },
  {
    "ContainingType": "AcountService.Controllers.UserController",
    "Method": "UpdateUser",
    "RelativePath": "api/User/{id}",
    "HttpMethod": "PUT",
    "IsController": true,
    "Order": 0,
    "Parameters": [
      {
        "Name": "id",
        "Type": "System.String",
        "IsRequired": true
      },
      {
        "Name": "request",
        "Type": "AcountService.dto.request.accountservice.UserUpdateRequest",
        "IsRequired": true
      }
    ],
    "ReturnTypes": []
  },
  {
    "ContainingType": "AcountService.Controllers.UserController",
    "Method": "DeleteUser",
    "RelativePath": "api/User/{id}",
    "HttpMethod": "DELETE",
    "IsController": true,
    "Order": 0,
    "Parameters": [
      {
        "Name": "id",
        "Type": "System.String",
        "IsRequired": true
      }
    ],
    "ReturnTypes": []
  },
  {
    "ContainingType": "AcountService.Controllers.UserController",
    "Method": "CreateUser",
    "RelativePath": "api/User/create",
    "HttpMethod": "POST",
    "IsController": true,
    "Order": 0,
    "Parameters": [
      {
        "Name": "userCreateRequest",
        "Type": "AcountService.dto.request.accountservice.UserCreateRequest",
        "IsRequired": true
      }
    ],
    "ReturnTypes": []
  },
  {
    "ContainingType": "AcountService.Controllers.UserController",
    "Method": "GetAllUsers",
    "RelativePath": "api/User/users",
    "HttpMethod": "GET",
    "IsController": true,
    "Order": 0,
    "Parameters": [],
    "ReturnTypes": []
  }
]